{
  "th": 268,
  "he": 312,
  "of": 52,
  "an": 755,
  "nd": 394,
  "in": 1552,
  "fo": 145,
  "or": 712,
  "is": 471,
  "on": 1181,
  "ha": 240,
  "at": 947,
  "by": 17,
  "hi": 214,
  "wi": 100,
  "it": 535,
  "yo": 17,
  "ou": 318,
  "no": 158,
  "ot": 201,
  "be": 168,
  "ar": 679,
  "re": 1146,
  "fr": 60,
  "ro": 453,
  "om": 309,
  "as": 319,
  "ur": 341,
  "al": 725,
  "ll": 324,
  "av": 72,
  "ve": 492,
  "ne": 449,
  "ew": 71,
  "mo": 196,
  "wa": 136,
  "we": 117,
  "il": 290,
  "ho": 234,
  "me": 474,
  "ca": 388,
  "ab": 175,
  "bo": 142,
  "ut": 209,
  "if": 111,
  "pa": 257,
  "ag": 167,
  "ge": 304,
  "se": 536,
  "ea": 432,
  "rc": 87,
  "ch": 324,
  "ee": 201,
  "bu": 108,
  "er": 1267,
  "do": 109,
  "nf": 53,
  "rm": 121,
  "ma": 331,
  "ti": 1221,
  "io": 734,
  "im": 186,
  "ey": 37,
  "si": 429,
  "te": 945,
  "up": 77,
  "ay": 107,
  "wh": 37,
  "ic": 515,
  "ei": 50,
  "ir": 183,
  "ws": 34,
  "us": 246,
  "ny": 37,
  "nl": 26,
  "ly": 274,
  "so": 178,
  "en": 952,
  "co": 681,
  "nt": 776,
  "ta": 439,
  "ac": 361,
  "ct": 363,
  "es": 1109,
  "ss": 295,
  "eb": 52,
  "ls": 126,
  "ow": 146,
  "el": 404,
  "lp": 19,
  "et": 307,
  "vi": 226,
  "ie": 321,
  "li": 519,
  "fi": 217,
  "rs": 369,
  "st": 723,
  "am": 195,
  "wo": 65,
  "ul": 168,
  "ld": 69,
  "rv": 63,
  "ce": 437,
  "cl": 138,
  "ck": 163,
  "ts": 325,
  "ik": 22,
  "ke": 157,
  "pr": 371,
  "ri": 611,
  "da": 138,
  "ba": 166,
  "to": 317,
  "op": 163,
  "pe": 347,
  "eo": 31,
  "pl": 209,
  "le": 631,
  "ad": 257,
  "na": 292,
  "ju": 42,
  "ov": 121,
  "ye": 48,
  "em": 254,
  "ai": 241,
  "tw": 18,
  "lt": 85,
  "rl": 41,
  "ex": 175,
  "xt": 35,
  "ed": 852,
  "go": 68,
  "rk": 63,
  "la": 395,
  "os": 189,
  "od": 127,
  "du": 94,
  "uc": 101,
  "mu": 62,
  "uy": 8,
  "ak": 63,
  "sh": 227,
  "sy": 40,
  "ys": 55,
  "po": 251,
  "ci": 225,
  "ty": 158,
  "dd": 34,
  "ol": 280,
  "cy": 43,
  "nu": 66,
  "um": 121,
  "mb": 71,
  "su": 234,
  "va": 128,
  "bl": 186,
  "py": 14,
  "yr": 9,
  "ig": 189,
  "gh": 119,
  "ht": 79,
  "pp": 120,
  "rt": 248,
  "sa": 128,
  "af": 42,
  "ft": 34,
  "oo": 171,
  "id": 195,
  "de": 589,
  "pu": 80,
  "ub": 74,
  "ok": 62,
  "ks": 78,
  "sc": 152,
  "hr": 38,
  "ug": 68,
  "nk": 47,
  "ev": 128,
  "rd": 129,
  "ry": 163,
  "iv": 221,
  "ms": 53,
  "mp": 215,
  "gr": 151,
  "oe": 21,
  "un": 280,
  "ra": 672,
  "ni": 289,
  "ja": 17,
  "ua": 107,
  "fu": 70,
  "ap": 195,
  "og": 100,
  "fe": 143,
  "kn": 27,
  "ga": 123,
  "rn": 111,
  "tr": 396,
  "mm": 74,
  "lo": 326,
  "pm": 6,
  "ep": 137,
  "ff": 83,
  "ef": 110,
  "di": 421,
  "yp": 17,
  "ec": 388,
  "au": 86,
  "oc": 128,
  "ng": 852,
  "gn": 63,
  "dr": 71,
  "ph": 95,
  "ip": 106,
  "pi": 142,
  "bj": 9,
  "je": 35,
  "ru": 111,
  "fa": 106,
  "mi": 270,
  "sp": 183,
  "ia": 280,
  "bs": 48,
  "hn": 13,
  "gy": 30,
  "oj": 7,
  "wn": 35,
  "cu": 133,
  "oa": 73,
  "cc": 76,
  "rr": 124,
  "bi": 151,
  "aw": 37,
  "tu": 176,
  "iz": 67,
  "ze": 56,
  "nc": 305,
  "lu": 107,
  "ud": 62,
  "gu": 78,
  "ui": 92,
  "sm": 39,
  "nm": 13,
  "gi": 113,
  "tm": 21,
  "tl": 76,
  "cr": 167,
  "pt": 102,
  "ns": 529,
  "hy": 30,
  "qu": 120,
  "tt": 122,
  "eg": 109,
  "ue": 100,
  "jo": 24,
  "ob": 63,
  "oi": 53,
  "dv": 32,
  "gl": 40,
  "ox": 20,
  "ek": 15,
  "rg": 79,
  "ib": 97,
  "br": 113,
  "hu": 50,
  "eq": 41,
  "dy": 32,
  "db": 6,
  "ki": 92,
  "gs": 63,
  "ax": 21,
  "ym": 28,
  "rf": 29,
  "uo": 10,
  "xp": 65,
  "xa": 17,
  "sw": 32,
  "lw": 2,
  "wr": 16,
  "ps": 57,
  "ds": 125,
  "aj": 4,
  "gt": 11,
  "lm": 13,
  "lc": 17,
  "lf": 17,
  "hs": 13,
  "pd": 4,
  "lr": 4,
  "sk": 39,
  "cs": 41,
  "nn": 77,
  "sl": 56,
  "nv": 64,
  "yl": 16,
  "lk": 16,
  "eu": 23,
  "bm": 7,
  "tc": 39,
  "yt": 13,
  "wl": 11,
  "dg": 31,
  "az": 16,
  "zi": 16,
  "oy": 36,
  "fl": 72,
  "rp": 36,
  "dw": 11,
  "gd": 1,
  "uf": 19,
  "wt": 3,
  "ka": 16,
  "lb": 12,
  "dm": 16,
  "xc": 28,
  "za": 25,
  "vo": 60,
  "tg": 4,
  "lv": 24,
  "xe": 29,
  "ix": 23,
  "dl": 38,
  "sd": 6,
  "dn": 7,
  "iq": 13,
  "xi": 31,
  "sf": 17,
  "tn": 12,
  "rw": 12,
  "yi": 30,
  "np": 3,
  "tb": 7,
  "tp": 5,
  "eh": 18,
  "aq": 6,
  "td": 4,
  "kg": 2,
  "yb": 8,
  "bt": 7,
  "yw": 6,
  "iu": 20,
  "nj": 12,
  "kt": 3,
  "oh": 6,
  "zo": 12,
  "my": 17,
  "pf": 1,
  "hl": 13,
  "ya": 19,
  "kl": 10,
  "sq": 5,
  "rh": 8,
  "dc": 8,
  "sr": 4,
  "ae": 6,
  "rb": 33,
  "pg": 4,
  "tf": 7,
  "vy": 2,
  "gg": 25,
  "kf": 4,
  "mn": 7,
  "fy": 15,
  "sn": 10,
  "ii": 3,
  "ko": 7,
  "wy": 2,
  "hd": 5,
  "zz": 8,
  "yc": 16,
  "ah": 7,
  "yn": 12,
  "hc": 2,
  "mf": 3,
  "km": 3,
  "ky": 8,
  "ux": 6,
  "xu": 2,
  "kb": 4,
  "yd": 5,
  "dt": 4,
  "ku": 5,
  "hb": 5,
  "lg": 8,
  "hw": 9,
  "sb": 3,
  "zy": 5,
  "pc": 1,
  "nr": 7,
  "nh": 14,
  "tz": 1,
  "cz": 1,
  "xf": 1,
  "iw": 1,
  "bb": 11,
  "uv": 2,
  "cq": 5,
  "kj": 1,
  "hm": 13,
  "kr": 3,
  "xh": 5,
  "nw": 7,
  "nq": 5,
  "bv": 2,
  "gm": 7,
  "kp": 2,
  "uk": 5,
  "hv": 1,
  "uu": 1,
  "bn": 3,
  "nb": 6,
  "uz": 6,
  "zl": 2,
  "qi": 1,
  "fg": 2,
  "mc": 2,
  "gb": 1,
  "bc": 5,
  "dh": 3,
  "fs": 7,
  "wd": 3,
  "sg": 2,
  "ln": 6,
  "dj": 6,
  "xy": 3,
  "yg": 3,
  "dq": 1,
  "ez": 5,
  "zu": 1,
  "lh": 1,
  "yh": 1,
  "bw": 2,
  "nz": 4,
  "xo": 2,
  "oz": 5,
  "nx": 2,
  "ij": 3,
  "ji": 2,
  "bd": 2,
  "ej": 4,
  "vu": 3,
  "wc": 1,
  "yz": 4,
  "ao": 3,
  "uw": 1,
  "tv": 1,
  "gk": 1,
  "wb": 6,
  "dp": 1,
  "kd": 1,
  "gf": 1,
  "kh": 2,
  "qa": 1,
  "wk": 1,
  "zb": 1,
  "hq": 1,
  "cn": 2,
  "yu": 2,
  "bp": 1,
  "ih": 1,
  "wf": 1,
  "mw": 2,
  "uq": 1,
  "bh": 1,
  "yf": 1,
  "hf": 1,
  "rz": 1,
  "kw": 4,
  "ml": 2,
  "df": 2,
  "wp": 1,
  "pk": 1,
  "pb": 1,
  "xq": 1,
  "pw": 1
}